pycsemri/libdecomposeGivenFieldMapAndDampings.so
pycsemri/libgraphCutIterations.so
pycsemri/getQuadraticApprox.py
pycsemri/graphCutIterations.py
pycsemri/estimateR2starGivenFieldmap.py
pycsemri/fwFit_MixedLS_1r2star.py
pycsemri/computeFF.py
pycsemri/decomposeGivenFieldMapAndDampings.py
pycsemri/findLocalMinima.py
pycsemri/computeResidual.py
pycsemri/__init__.py
pycsemri/getPhiMatrixMultipeak.py
pycsemri/libuwwfs.so
pycsemri/create_robust_mask.py
pycsemri/fwFit_MagnLS_1r2star.py
pycsemri/createExpansionGraphVARPRO_fast.py
pycsemri/fw_i2cm1i_graphcut.py
pycsemri/fwFit_ComplexLS_1r2star.py
pycsemri-0.1.9.dist-info/WHEEL
pycsemri-0.1.9.dist-info/top_level.txt
pycsemri-0.1.9.dist-info/RECORD
pycsemri-0.1.9.dist-info/METADATA
pycsemri-0.1.9.dist-info/licenses/LICENSE.md
pycsemri.libs/libstdc++-496613c0.so.6.0.32
pycsemri.libs/libgcc_s-a3a07607.so.1
