Metadata-Version: 2.1
Name: pycsemri
Version: 0.1.9
Summary: A package for CSEMRI with C++ accelerated components.
Home-page: https://github.com/your-username/PyCSEMRI_fast
Author: Daiki Tamada
Author-email: dtamada@wisc.edu
License: GPL
Platform: UNKNOWN
Requires-Python: >=3.6
License-File: LICENSE.md
Requires-Dist: numpy (<1.20) ; python_version == "3.6"
Requires-Dist: numpy ; python_version >= "3.7"
